<?xml version="1.0" encoding="utf-8" ?>
<dwsync>
<file name="leftNavOFF.png" server="E:/xampp/apache" local="130373271496792222" remote="130373271490000000" Dst="2" />
<file name="leftNavON.png" server="E:/xampp/apache" local="130373271496872227" remote="130373271490000000" Dst="2" />
<file name="rightNavOFF.png" server="E:/xampp/apache" local="130373271496942231" remote="130373271490000000" Dst="2" />
<file name="rightNavON.png" server="E:/xampp/apache" local="130373271497022235" remote="130373271490000000" Dst="2" />
<file name="bottomNavOFF.png" server="E:/xampp/apache" local="130373271496242191" remote="130373271490000000" Dst="2" />
<file name="bottomNavON.png" server="E:/xampp/apache" local="130373271496412201" remote="130373271490000000" Dst="2" />
<file name="bottomNavLeft.png" server="E:/xampp/apache" local="130373271496162186" remote="130373271490000000" Dst="2" />
<file name="bottomNavRight.png" server="E:/xampp/apache" local="130373271496632213" remote="130373271490000000" Dst="2" />
<file name="bottomOverThumbBg.png" server="E:/xampp/apache" local="130373271496712218" remote="130373271490000000" Dst="2" />
</dwsync>